{
  "config": "{\"version\":\"5.59\",\"themeCollection\":{\"baseTheme\":{\"name\":\"CY24SU10\",\"type\":2,\"version\":\"5.59\"}},\"activeSectionIndex\":0,\"defaultDrillFilterOtherVisuals\":true,\"settings\":{\"useNewFilterPaneExperience\":true,\"allowChangeFilterTypes\":true,\"useStylableVisualContainerHeader\":true,\"queryLimitOption\":6,\"useEnhancedTooltips\":true,\"exportDataMode\":1,\"useDefaultAggregateDisplayName\":true,\"filterPaneHiddenInEditMode\":true},\"objects\":{\"section\":[{\"properties\":{\"verticalAlignment\":{\"expr\":{\"Literal\":{\"Value\":\"'Top'\"}}}}}]}}",
  "layoutOptimization": 0,
  "resourcePackages": [
    {
      "resourcePackage": {
        "disabled": false,
        "items": [
          {
            "name": "CY24SU10",
            "path": "BaseThemes/CY24SU10.json",
            "type": 202
          }
        ],
        "name": "SharedResources",
        "type": 2
      }
    }
  ],
  "sections": [
    {
      "config": "{}",
      "displayName": "Page 1",
      "displayOption": 1,
      "filters": "[]",
      "height": 720.00,
      "name": "620f60ccfb1ea593feb6",
      "visualContainers": [
        {
          "config": "{\"name\":\"b3fa57431fce33205552\",\"layouts\":[{\"id\":0,\"position\":{\"x\":8,\"y\":8,\"z\":1,\"width\":136,\"height\":440,\"tabOrder\":1}}],\"singleVisual\":{\"visualType\":\"slicer\",\"projections\":{\"Values\":[{\"queryRef\":\"moedas.Moeda\",\"active\":true}]},\"prototypeQuery\":{\"Version\":2,\"From\":[{\"Name\":\"m\",\"Entity\":\"moedas\",\"Type\":0}],\"Select\":[{\"Column\":{\"Expression\":{\"SourceRef\":{\"Source\":\"m\"}},\"Property\":\"Moeda\"},\"Name\":\"moedas.Moeda\",\"NativeReferenceName\":\"Moeda\"}]},\"drillFilterOtherVisuals\":true,\"objects\":{\"data\":[{\"properties\":{\"mode\":{\"expr\":{\"Literal\":{\"Value\":\"'Basic'\"}}}}}],\"general\":[{\"properties\":{\"filter\":{\"filter\":{\"Version\":2,\"From\":[{\"Name\":\"m\",\"Entity\":\"moedas\",\"Type\":0}],\"Where\":[{\"Condition\":{\"In\":{\"Expressions\":[{\"Column\":{\"Expression\":{\"SourceRef\":{\"Source\":\"m\"}},\"Property\":\"Moeda\"}}],\"Values\":[[{\"Literal\":{\"Value\":\"'USD'\"}}]]}}}]}}}}]}}}",
          "filters": "[]",
          "height": 440.00,
          "width": 136.00,
          "x": 8.00,
          "y": 8.00,
          "z": 1.00
        },
        {
          "config": "{\"name\":\"becf635ac233b276157f\",\"layouts\":[{\"id\":0,\"position\":{\"x\":328,\"y\":8,\"z\":0,\"width\":624,\"height\":680}}],\"singleVisual\":{\"visualType\":\"tableEx\",\"projections\":{\"Values\":[{\"queryRef\":\"calendario.Data\"},{\"queryRef\":\"transacoes.Valor Total\"},{\"queryRef\":\"cotacoes.Cotação do dia\"},{\"queryRef\":\"cotacoes.Cotação corrigida\"},{\"queryRef\":\"transacoes.Total R$\"}]},\"prototypeQuery\":{\"Version\":2,\"From\":[{\"Name\":\"c1\",\"Entity\":\"calendario\",\"Type\":0},{\"Name\":\"t\",\"Entity\":\"transacoes\",\"Type\":0},{\"Name\":\"c\",\"Entity\":\"cotacoes\",\"Type\":0}],\"Select\":[{\"Column\":{\"Expression\":{\"SourceRef\":{\"Source\":\"c1\"}},\"Property\":\"Data\"},\"Name\":\"calendario.Data\",\"NativeReferenceName\":\"Data\"},{\"Measure\":{\"Expression\":{\"SourceRef\":{\"Source\":\"t\"}},\"Property\":\"Valor Total\"},\"Name\":\"transacoes.Valor Total\",\"NativeReferenceName\":\"Valor Total\"},{\"Measure\":{\"Expression\":{\"SourceRef\":{\"Source\":\"c\"}},\"Property\":\"Cotação do dia\"},\"Name\":\"cotacoes.Cotação do dia\",\"NativeReferenceName\":\"Cotação do dia\"},{\"Measure\":{\"Expression\":{\"SourceRef\":{\"Source\":\"t\"}},\"Property\":\"Cotação corrigida\"},\"Name\":\"cotacoes.Cotação corrigida\",\"NativeReferenceName\":\"Cotação corrigida\"},{\"Measure\":{\"Expression\":{\"SourceRef\":{\"Source\":\"t\"}},\"Property\":\"Total R$\"},\"Name\":\"transacoes.Total R$\",\"NativeReferenceName\":\"Total R$\"}],\"OrderBy\":[{\"Direction\":1,\"Expression\":{\"Column\":{\"Expression\":{\"SourceRef\":{\"Source\":\"c1\"}},\"Property\":\"Data\"}}}]},\"drillFilterOtherVisuals\":true,\"objects\":{}}}",
          "filters": "[]",
          "height": 680.00,
          "width": 624.00,
          "x": 328.00,
          "y": 8.00,
          "z": 0.00
        }
      ],
      "width": 1280.00
    }
  ]
}